LICENSE
MANIFEST.in
README.md
setup.py
choicesfilter/__init__.py
choicesfilter/admin.py
choicesfilter/static/choicesfilter/js/choicesfilter.js
choicesfilter/templates/choicesfilter.html
twentytab_choicesfilter.egg-info/PKG-INFO
twentytab_choicesfilter.egg-info/SOURCES.txt
twentytab_choicesfilter.egg-info/dependency_links.txt
twentytab_choicesfilter.egg-info/requires.txt
twentytab_choicesfilter.egg-info/top_level.txt