Metadata-Version: 1.0
Name: twentytab-choicesfilter
Version: 0.8.2
Summary: A django app that initializes admin changelist view with select filters usin jquery-plugin select2
Home-page: https://github.com/20tab/twentytab-choicesfilter
Author: 20tab S.r.l.
Author-email: info@20tab.com
License: MIT License
Platform: UNKNOWN
